{
  "project_info": {
    "project_number": "477395312345",
    "firebase_url": "https://esamudaay-customer.firebaseio.com",
    "project_id": "esamudaay-customer",
    "storage_bucket": "esamudaay-customer.appspot.com"
  },
  "client": [
    {
      "client_info": {
        "mobilesdk_app_id": "1:477395312345:android:1a7e7f3a80d216ad66e8c8",
        "android_client_info": {
          "package_name": "com.esamudaay.customer"
        }
      },
      "oauth_client": [
        {
          "client_id": "477395312345-9tlr75m4kelqdgau4n8uuk6s3q07hiln.apps.googleusercontent.com",
          "client_type": 3
        }
      ],
      "api_key": [
        {
          "current_key": "AIzaSyCB5eWzRLndIZxpn_XmuyweL6_VPlSuKIE"
        }
      ],
      "services": {
        "appinvite_service": {
          "other_platform_oauth_client": [
            {
              "client_id": "477395312345-9tlr75m4kelqdgau4n8uuk6s3q07hiln.apps.googleusercontent.com",
              "client_type": 3
            },
            {
              "client_id": "477395312345-ak0esb1ns2ca9jogtv2pe47868rgrahn.apps.googleusercontent.com",
              "client_type": 2,
              "ios_info": {
                "bundle_id": "com.esamudaay.customer"
              }
            }
          ]
        }
      }
    }
  ],
  "configuration_version": "1"
}